[
  {
    "lectureCode": "GH3001",
    "courseName": "医療技術学研究企画",
    "lecturer": [
      "岡崎充宏(医療保健学部臨床検査学科)",
      "篠原一彦(医療保健学部臨床工学科)",
      "佐々木聰(医療保健学部臨床検査学科)",
      "苗村潔(医療保健学部臨床工学科)",
      "日向奈惠(医療保健学部臨床工学科)",
      "栗原由利子(医療保健学部臨床検査学科)",
      "廣田雅子(医療保健学部臨床検査学科)",
      "中川和美(医療保健学部リハビリテーション学科作業療法学専攻)",
      "田仲浩平(医療保健学部臨床工学科)",
      "榎本みのり(医療保健学部臨床検査学科)",
      "十島純子(医療保健学部リハビリテーション学科理学療法学専攻)",
      "澤田辰徳(医療保健学部リハビリテーション学科作業療法学専攻)",
      "笠井亮佑(医療保健学部臨床工学科)",
      "友利幸之介(医療保健学部リハビリテーション学科作業療法学専攻)",
      "島峰徹也(医療保健学部臨床工学科)",
      "清水潤(医療保健学部リハビリテーション学科理学療法学専攻)",
      "川又紀彦(医療保健学部臨床検査学科)"
    ],
    "regularOrIntensive": "研究科目",
    "courseType": "演習科目",
    "courseStart": "2025年度前期",
    "classPeriod": [
      "他"
    ],
    "targetDepartment": "医療技術学研究科修士課程臨床検査学専攻",
    "targetGrade": [
      "1年",
      "2年"
    ],
    "numberOfCredits": 2,
    "classroom": [
      ""
    ],
    "updateAt": "2025/03/21",
    "search_times": []
  },
  {
    "lectureCode": "GH3002",
    "courseName": "医療技術学研究I",
    "lecturer": [
      "岡崎充宏(医療保健学部臨床検査学科)",
      "篠原一彦(医療保健学部臨床工学科)",
      "佐々木聰(医療保健学部臨床検査学科)",
      "苗村潔(医療保健学部臨床工学科)",
      "日向奈惠(医療保健学部臨床工学科)",
      "栗原由利子(医療保健学部臨床検査学科)",
      "廣田雅子(医療保健学部臨床検査学科)",
      "中川和美(医療保健学部リハビリテーション学科作業療法学専攻)",
      "田仲浩平(医療保健学部臨床工学科)",
      "榎本みのり(医療保健学部臨床検査学科)",
      "十島純子(医療保健学部リハビリテーション学科理学療法学専攻)",
      "澤田辰徳(医療保健学部リハビリテーション学科作業療法学専攻)",
      "友利幸之介(医療保健学部リハビリテーション学科作業療法学専攻)",
      "島峰徹也(医療保健学部臨床工学科)",
      "清水潤(医療保健学部リハビリテーション学科理学療法学専攻)",
      "川又紀彦(医療保健学部臨床検査学科)"
    ],
    "regularOrIntensive": "研究科目",
    "courseType": "演習科目",
    "courseStart": "2025年度後期",
    "classPeriod": [
      "他"
    ],
    "targetDepartment": "医療技術学研究科修士課程臨床検査学専攻",
    "targetGrade": [
      "1年",
      "2年"
    ],
    "numberOfCredits": 4,
    "classroom": [
      ""
    ],
    "updateAt": "2025/03/21",
    "search_times": []
  },
  {
    "lectureCode": "GH3003",
    "courseName": "医療技術学研究II",
    "lecturer": [
      "岡崎充宏(医療保健学部臨床検査学科)",
      "篠原一彦(医療保健学部臨床工学科)",
      "佐々木聰(医療保健学部臨床検査学科)",
      "苗村潔(医療保健学部臨床工学科)",
      "日向奈惠(医療保健学部臨床工学科)",
      "栗原由利子(医療保健学部臨床検査学科)",
      "廣田雅子(医療保健学部臨床検査学科)",
      "中川和美(医療保健学部リハビリテーション学科作業療法学専攻)",
      "田仲浩平(医療保健学部臨床工学科)",
      "榎本みのり(医療保健学部臨床検査学科)",
      "十島純子(医療保健学部リハビリテーション学科理学療法学専攻)",
      "澤田辰徳(医療保健学部リハビリテーション学科作業療法学専攻)",
      "友利幸之介(医療保健学部リハビリテーション学科作業療法学専攻)",
      "島峰徹也(医療保健学部臨床工学科)",
      "清水潤(医療保健学部リハビリテーション学科理学療法学専攻)",
      "川又紀彦(医療保健学部臨床検査学科)"
    ],
    "regularOrIntensive": "研究科目",
    "courseType": "演習科目",
    "courseStart": "2025年度前期",
    "classPeriod": [
      "他"
    ],
    "targetDepartment": "医療技術学研究科修士課程臨床検査学専攻",
    "targetGrade": [
      "2年"
    ],
    "numberOfCredits": 4,
    "classroom": [
      ""
    ],
    "updateAt": "2025/03/21",
    "search_times": []
  },
  {
    "lectureCode": "GH3004",
    "courseName": "医療技術学研究III",
    "lecturer": [
      "岡崎充宏(医療保健学部臨床検査学科)",
      "篠原一彦(医療保健学部臨床工学科)",
      "佐々木聰(医療保健学部臨床検査学科)",
      "苗村潔(医療保健学部臨床工学科)",
      "日向奈惠(医療保健学部臨床工学科)",
      "栗原由利子(医療保健学部臨床検査学科)",
      "廣田雅子(医療保健学部臨床検査学科)",
      "中川和美(医療保健学部リハビリテーション学科作業療法学専攻)",
      "田仲浩平(医療保健学部臨床工学科)",
      "榎本みのり(医療保健学部臨床検査学科)",
      "十島純子(医療保健学部リハビリテーション学科理学療法学専攻)",
      "澤田辰徳(医療保健学部リハビリテーション学科作業療法学専攻)",
      "友利幸之介(医療保健学部リハビリテーション学科作業療法学専攻)",
      "島峰徹也(医療保健学部臨床工学科)",
      "清水潤(医療保健学部リハビリテーション学科理学療法学専攻)",
      "川又紀彦(医療保健学部臨床検査学科)"
    ],
    "regularOrIntensive": "研究科目",
    "courseType": "演習科目",
    "courseStart": "2025年度後期",
    "classPeriod": [
      "他"
    ],
    "targetDepartment": "医療技術学研究科修士課程臨床検査学専攻",
    "targetGrade": [
      "2年"
    ],
    "numberOfCredits": 4,
    "classroom": [
      ""
    ],
    "updateAt": "2025/03/21",
    "search_times": []
  }
]